{"nm":"absract 3","ddd":0,"h":1000,"w":1000,"meta":{"g":"@lottiefiles/toolkit-js 0.26.1"},"layers":[{"ty":5,"nm":"LOGO ","sr":1,"st":0,"op":250,"ip":0,"hd":false,"ddd":0,"bm":0,"hasMask":false,"ao":0,"ks":{"a":{"a":0,"k":[0,0,0],"ix":1},"s":{"a":0,"k":[100,100,100],"ix":6},"sk":{"a":0,"k":0},"p":{"a":0,"k":[50,160,0],"ix":2},"r":{"a":0,"k":0,"ix":10},"sa":{"a":0,"k":0},"o":{"a":0,"k":100,"ix":11}},"ef":[],"t":{"m":{"a":{"a":0,"k":[0,0],"ix":2},"g":1},"p":{},"a":[],"d":{"k":[{"s":{"f":"SegoeUI-Bold","s":50,"t":"","fc":[1,1,1],"lh":50,"tr":0,"j":2,"ca":0},"t":0}]}},"ind":1,"parent":2},{"ty":4,"nm":"square","sr":1,"st":0,"op":250,"ip":0,"hd":false,"ddd":0,"bm":0,"hasMask":false,"ao":0,"ks":{"a":{"a":0,"k":[-30,7,0],"ix":1},"s":{"a":0,"k":[100,100,100],"ix":6},"sk":{"a":0,"k":0},"p":{"a":0,"k":[500,500,0],"ix":2},"r":{"a":0,"k":0,"ix":10},"sa":{"a":0,"k":0},"o":{"a":0,"k":100,"ix":11}},"ef":[],"shapes":[{"ty":"gr","bm":0,"hd":false,"mn":"ADBE Vector Group","nm":"Rectangle 1","ix":1,"cix":2,"np":2,"it":[{"ty":"rc","bm":0,"hd":false,"mn":"ADBE Vector Shape - Rect","nm":"Rectangle Path 1","d":1,"p":{"a":0,"k":[-27,16],"ix":3},"r":{"a":0,"k":0,"ix":4},"s":{"a":0,"k":[366,366],"ix":2}},{"ty":"gf","bm":0,"hd":false,"mn":"ADBE Vector Graphic - G-Fill","nm":"Gradient Fill 1","e":{"a":0,"k":[113,-119],"ix":6},"g":{"p":3,"k":{"a":0,"k":[0,0.25098039215686274,0.48627450980392156,1,0.5,0.25098039215686274,0.48627450980392156,1,1,0.8549019607843137,0.5450980392156862,1],"ix":9}},"t":1,"a":{"a":0,"k":0},"h":{"a":0,"k":0},"s":{"a":0,"k":[-204,198],"ix":5},"r":1,"o":{"a":0,"k":100,"ix":10}},{"ty":"tr","a":{"a":0,"k":[0,0],"ix":1},"s":{"a":0,"k":[100,100],"ix":3},"sk":{"a":0,"k":0,"ix":4},"p":{"a":0,"k":[-3,-9],"ix":2},"r":{"a":0,"k":0,"ix":6},"sa":{"a":0,"k":0,"ix":5},"o":{"a":0,"k":100,"ix":7}}]}],"ind":2},{"ty":4,"nm":"lines","sr":1,"st":0,"op":250,"ip":0,"hd":false,"ddd":0,"bm":0,"hasMask":false,"ao":0,"ks":{"a":{"a":0,"k":[0,0,0],"ix":1},"s":{"a":0,"k":[100,100,100],"ix":6},"sk":{"a":0,"k":0},"p":{"a":0,"k":[-18,0,0],"ix":2},"r":{"a":0,"k":0,"ix":10},"sa":{"a":0,"k":0},"o":{"a":0,"k":100,"ix":11}},"ef":[],"shapes":[{"ty":"gr","bm":0,"hd":false,"mn":"ADBE Vector Group","nm":"Shape 1","ix":1,"cix":2,"np":3,"it":[{"ty":"sh","bm":0,"hd":false,"mn":"ADBE Vector Shape - Group","nm":"Path 1","ix":1,"d":1,"ks":{"a":1,"k":[{"o":{"x":0.167,"y":0.167},"i":{"x":0.833,"y":0.833},"s":[{"c":true,"i":[[194,35],[95.241,13.606],[29,-98],[41,-88],[-154.634,-30.927],[-95.227,-26.301],[-77,114],[25.604,63.643]],"o":[[-105.498,-19.033],[-112,-16],[-25.281,85.433],[-34.672,74.417],[140,28],[105,29],[53.059,-78.554],[-35,-87]],"v":[[318,-398],[60,-233],[-305,-196],[-219,-46],[-316,422],[-76,226],[258,258],[211,80]]}],"t":0},{"o":{"x":0.167,"y":0.167},"i":{"x":0.833,"y":0.833},"s":[{"c":true,"i":[[45.527,29.807],[104.973,162.215],[28.495,-141.06],[-35.004,-158.383],[-0.416,-85.044],[-99.336,-112.198],[-21.847,128.417],[57.889,91.548]],"o":[[-109.635,-59.6],[-93.213,-147.305],[-25.843,127.931],[17.548,79.159],[0.187,118.333],[99.336,112.198],[20.669,-121.496],[-60.712,-96.011]],"v":[[246.488,-247.386],[-56.787,-252.695],[-398.495,-350.94],[-204.077,66.151],[-356.814,288.161],[12.664,247.802],[363.331,329.496],[219.712,38.011]]}],"t":93},{"o":{"x":0.167,"y":0.167},"i":{"x":0.833,"y":0.833},"s":[{"c":true,"i":[[52.716,27.001],[134,-55],[63,-62],[189.244,-110.507],[-62,-62],[-120.935,97.973],[-132.548,50.98],[-109,72]],"o":[[-82,-42],[-115.875,47.56],[-63.502,62.494],[-137,80],[57.009,57.009],[158,-128],[182,-70],[127.51,-84.227]],"v":[[216,-260],[-64,-211],[-291,-266],[-271,50],[-370,302],[-48,230],[328,388],[207,-76]]}],"t":167},{"s":[{"c":true,"i":[[194,35],[95.241,13.606],[29,-98],[41,-88],[-154.634,-30.927],[-95.227,-26.301],[-77,114],[25.604,63.643]],"o":[[-105.498,-19.033],[-112,-16],[-25.281,85.433],[-34.672,74.417],[140,28],[105,29],[53.059,-78.554],[-35,-87]],"v":[[318,-398],[60,-233],[-305,-196],[-219,-46],[-316,422],[-76,226],[258,258],[211,80]]}],"t":250}],"ix":2}},{"ty":"gs","bm":0,"hd":false,"mn":"ADBE Vector Graphic - G-Stroke","nm":"Gradient Stroke 1","e":{"a":0,"k":[198,-229],"ix":5},"g":{"p":3,"k":{"a":0,"k":[0,0.984313725490196,0.44313725490196076,0.5215686274509804,0.5,0.25098039215686274,0.48627450980392156,1,1,0.8549019607843137,0.5450980392156862,1],"ix":8}},"t":1,"a":{"a":0,"k":0},"h":{"a":0,"k":0},"s":{"a":0,"k":[-492,306],"ix":4},"lc":1,"lj":1,"ml":4,"o":{"a":0,"k":100,"ix":9},"w":{"a":0,"k":2,"ix":10}},{"ty":"rp","bm":0,"hd":false,"mn":"ADBE Vector Filter - Repeater","nm":"Repeater 1","ix":3,"m":1,"c":{"a":0,"k":26,"ix":1},"o":{"a":0,"k":0,"ix":2},"tr":{"a":{"a":0,"k":[0,0],"ix":1},"s":{"a":1,"k":[{"o":{"x":0.167,"y":0.167},"i":{"x":0.833,"y":0.833},"s":[96,96],"t":0},{"o":{"x":0.167,"y":0.167},"i":{"x":0.833,"y":0.833},"s":[97,97],"t":122},{"s":[96,96],"t":249}],"ix":3},"sk":{"a":0,"k":0},"p":{"a":1,"k":[{"o":{"x":0.167,"y":0.167},"i":{"x":0.833,"y":0.833},"s":[-1.5,0],"t":0,"ti":[0,0],"to":[0,0]},{"o":{"x":0.167,"y":0.167},"i":{"x":0.833,"y":0.833},"s":[0.5,0],"t":122,"ti":[0,0],"to":[0,0]},{"s":[-1.5,0],"t":249}],"ix":2},"r":{"a":0,"k":0,"ix":4},"sa":{"a":0,"k":0},"so":{"a":0,"k":85,"ix":5},"eo":{"a":0,"k":100,"ix":6}}},{"ty":"tr","a":{"a":0,"k":[0,0],"ix":1},"s":{"a":0,"k":[100,100],"ix":3},"sk":{"a":0,"k":0,"ix":4},"p":{"a":0,"k":[0,0],"ix":2},"r":{"a":0,"k":0,"ix":6},"sa":{"a":0,"k":0,"ix":5},"o":{"a":0,"k":100,"ix":7}}]}],"ind":3,"parent":2}],"v":"5.7.3","fr":25,"op":250,"ip":0,"fonts":{"list":[{"ascent":74.0234375,"fClass":"","fFamily":"Segoe UI","fStyle":"Bold","fName":"SegoeUI-Bold","fPath":"","fWeight":"","origin":1}]},"assets":[]}